{
  "version": "7",
  "dialect": "postgresql",
  "entries": [
    {
      "idx": 0,
      "version": "7",
      "when": 1769725123921,
      "tag": "0000_initial",
      "breakpoints": true
    },
    {
      "idx": 1,
      "version": "7",
      "when": 1772294986086,
      "tag": "0001_good_invisible_woman",
      "breakpoints": true
    },
    {
      "idx": 2,
      "version": "7",
      "when": 1772726400000,
      "tag": "0002_skills_address_rename",
      "breakpoints": true
    },
    {
      "idx": 3,
      "version": "7",
      "when": 1772813400000,
      "tag": "0003_token_skills_address",
      "breakpoints": true
    }
  ]
}